hephaistos/__init__.py
hephaistos/__init__.pyi
hephaistos/glsl.py
hephaistos/pipeline.py
hephaistos/py.typed
hephaistos/pyhephaistos.cp39-win_amd64.pyd
hephaistos/pyhephaistos.pyi
hephaistos/queue.py
hephaistos/util.py
hephaistos-0.10.1.dist-info/METADATA
hephaistos-0.10.1.dist-info/WHEEL
hephaistos-0.10.1.dist-info/licenses/LICENSE
hephaistos-0.10.1.dist-info/licenses/external/NOTICE
hephaistos-0.10.1.dist-info/licenses/external/glslang/LICENSE.txt
hephaistos-0.10.1.dist-info/licenses/external/nanobind/LICENSE
hephaistos-0.10.1.dist-info/licenses/external/reflect/LICENSE
hephaistos-0.10.1.dist-info/licenses/external/stb/LICENSE
hephaistos-0.10.1.dist-info/licenses/external/vma/LICENSE.txt
hephaistos-0.10.1.dist-info/licenses/external/volk/LICENSE.md
hephaistos-0.10.1.dist-info/licenses/external/vulkan/LICENSE.txt
hephaistos-0.10.1.dist-info/RECORD
