Metadata-Version: 2.1
Name: hephaistos
Version: 0.10.1
Summary: GPU computing framework using the Vulkan API
Author-Email: Kerscher Tobias <88444139+tkerscher@users.noreply.github.com>
Classifier: Development Status :: 4 - Beta
Classifier: Environment :: GPU
Classifier: License :: OSI Approved :: MIT License
Classifier: Programming Language :: C++
Classifier: Programming Language :: Python
Requires-Python: >=3.8
